{
    "spreadsheet": "6_sharris0700wk3.xlsx",
    "tables": [
        {
            "table_id": "table_1",
            "bounding_box": {
                "top_row": 0,
                "bottom_row": 1,
                "left_col": 0,
                "right_col": 1
            }
        },
        {
            "table_id": "table_2",
            "bounding_box": {
                "top_row": 6,
                "bottom_row": 24,
                "left_col": 0,
                "right_col": 4
            }
        },
        {
            "table_id": "table_3",
            "bounding_box": {
                "top_row": 29,
                "bottom_row": 35,
                "left_col": 0,
                "right_col": 3
            }
        }
    ]
}